httpdate/__about__.py
httpdate/__init__.py
httpdate/httpdate.py
httpdate/py.typed
httpdate-1.2.0.dist-info/METADATA
httpdate-1.2.0.dist-info/WHEEL
httpdate-1.2.0.dist-info/licenses/LICENSE
httpdate-1.2.0.dist-info/RECORD
