Metadata-Version: 2.1
Name: httpdate
Version: 1.2.0
Summary: Parse and format HTTP dates, such as Last-Modified and If-Modified-Since headers.
Project-URL: Homepage, https://github.com/jamielinux/httpdate
Project-URL: Issues, https://github.com/jamielinux/httpdate/issues
Project-URL: Source, https://github.com/jamielinux/httpdate
Author-email: Jamie Nguyen <j@jamielinux.com>
License-Expression: MIT
License-File: LICENSE
Keywords: if-modified-since,last-modified,lastmodified,rfc9110
Classifier: Development Status :: 5 - Production/Stable
Classifier: Intended Audience :: Developers
Classifier: License :: OSI Approved :: MIT License
Classifier: Programming Language :: Python
Classifier: Programming Language :: Python :: 3.7
Classifier: Programming Language :: Python :: 3.8
Classifier: Programming Language :: Python :: 3.9
Classifier: Programming Language :: Python :: 3.10
Classifier: Programming Language :: Python :: 3.11
Classifier: Programming Language :: Python :: Implementation :: CPython
Classifier: Programming Language :: Python :: Implementation :: PyPy
Classifier: Topic :: Software Development :: Libraries
Requires-Python: >=3.7
Requires-Dist: leapseconds>=2023.4.0
